raccoon_simple_stopwatch/__init__.py
raccoon_simple_stopwatch/stopwatch.py
raccoon_simple_stopwatch/test/__init__.py
raccoon_simple_stopwatch/test/test_stopwatch.py
raccoon_simple_stopwatch-0.0.3.dist-info/METADATA
raccoon_simple_stopwatch-0.0.3.dist-info/WHEEL
raccoon_simple_stopwatch-0.0.3.dist-info/top_level.txt
raccoon_simple_stopwatch-0.0.3.dist-info/RECORD
