Metadata-Version: 2.1
Name: raccoon-simple-stopwatch
Version: 0.0.3
Summary: Raccoon Simple StopWatch
Home-page: https://github.com/brenordv/simple-stopwatch-package
Author: Breno RdV
Author-email: hello@raccoon.ninja
License: UNKNOWN
Project-URL: Bug Tracker, https://github.com/brenordv/simple-stopwatch-package/issues
Keywords: python,stopwatch,timer,elapsed
Platform: UNKNOWN
Classifier: Development Status :: 4 - Beta
Classifier: Intended Audience :: Developers
Classifier: License :: OSI Approved :: MIT License
Classifier: Programming Language :: Python :: 3
Classifier: Programming Language :: Python :: 3.6
Classifier: Programming Language :: Python :: 3.7
Classifier: Programming Language :: Python :: 3.8
Classifier: Programming Language :: Python :: 3.9
Classifier: Operating System :: MacOS :: MacOS X
Classifier: Operating System :: Microsoft :: Windows
Classifier: Operating System :: POSIX :: Linux
Requires-Dist: pytz
